{
    "interview": [
        {
            "name": "computer_tasks", 
            "tags": "important, research further", 
            "_rowNum": 2, 
            "param": null, 
            "label": "Tell me about some of the task your use computers for?", 
            "noNextLink": true, 
            "type": "none"
        }, 
        {
            "name": "computer_tasks_followup", 
            "tags": "important, research further", 
            "_rowNum": 3, 
            "type": "none", 
            "param": null, 
            "label": "What tasks do you find the most challenging or time consuming?"
        }
    ], 
    "links": [
        {
            "_rowNum": 2, 
            "label": "Does not use computers.", 
            "from": "computer_tasks", 
            "to": "interviewEnd"
        }, 
        {
            "_rowNum": 3, 
            "label": "Follow-up", 
            "from": "computer_tasks", 
            "to": "json/computer_tasks_followup"
        }
    ]
}